dclimate_client_py-0.5.3.dist-info/METADATA
dclimate_client_py-0.5.3.dist-info/WHEEL
dclimate_client_py-0.5.3.dist-info/entry_points.txt
dclimate_client_py-0.5.3.dist-info/licenses/LICENSE
dclimate_client_py/.pytest_cache/.gitignore
dclimate_client_py/.pytest_cache/CACHEDIR.TAG
dclimate_client_py/.pytest_cache/README.md
dclimate_client_py/.pytest_cache/v/cache/nodeids
dclimate_client_py/.pytest_cache/v/cache/stepwise
dclimate_client_py/__init__.py
dclimate_client_py/cids.json
dclimate_client_py/client.py
dclimate_client_py/concatenate.py
dclimate_client_py/datasets.py
dclimate_client_py/dclimate_client.py
dclimate_client_py/dclimate_zarr_errors.py
dclimate_client_py/encryption_codec.py
dclimate_client_py/geotemporal_data.py
dclimate_client_py/ipfs_retrieval.py
dclimate_client_py/s3_retrieval.py
dclimate_client_py/stac_catalog.py
dclimate_client_py/stac_server.py
dclimate_client_py/zarr_metadata.py
dclimate_client_py-0.5.3.dist-info/RECORD
