Metadata-Version: 2.1
Name: dclimate-client-py
Version: 0.5.3
Summary: Python client library for accessing dClimate weather and climate data
Keywords: climate,weather,data,dclimate,meteorology,climate-data
Author-Email: Phil Van Meppelen Scheppink <phil@dclimate.net>, Evan Schechter <evan@arbol.io>, Chris Rossi <chris@christophermrossi.com>, Robert Banick <robert.banick@arbol.io>
License: MIT
Classifier: Development Status :: 3 - Alpha
Classifier: Intended Audience :: Developers
Classifier: Intended Audience :: Science/Research
Classifier: License :: OSI Approved :: MIT License
Classifier: Programming Language :: Python :: 3
Classifier: Programming Language :: Python :: 3.12
Classifier: Topic :: Scientific/Engineering :: Atmospheric Science
Classifier: Topic :: Software Development :: Libraries :: Python Modules
Project-URL: Homepage, https://dclimate.net/
Requires-Python: >=3.12
Requires-Dist: aiobotocore
Requires-Dist: xarray>=2025.3.0
Requires-Dist: rioxarray
Requires-Dist: zarr>=3.0.8
Requires-Dist: numpy>=2.1.3
Requires-Dist: py_hamt>=3.3.1
Requires-Dist: requests
Requires-Dist: pyarrow
Requires-Dist: geopandas
Requires-Dist: pandas
Requires-Dist: s3fs
Requires-Dist: shapely
Requires-Dist: scipy
Requires-Dist: pycryptodome>=3.21.0
Requires-Dist: pystac>=1.10.0
Provides-Extra: testing
Requires-Dist: pytest; extra == "testing"
Requires-Dist: pytest-cov; extra == "testing"
Requires-Dist: pytest-mock; extra == "testing"
Requires-Dist: pytest-asyncio>=1.3.0; extra == "testing"
Provides-Extra: dev
Requires-Dist: pre-commit>=4.1.0; extra == "dev"
Requires-Dist: ruff>=0.9.5; extra == "dev"
